README.md
setup.py
CharActor/__init__.py
CharActor/__log__.py
CharActor/_character_bank.py
CharActor/_chardb.py
CharActor/_quiet_dict.py
CharActor.egg-info/PKG-INFO
CharActor.egg-info/SOURCES.txt
CharActor.egg-info/dependency_links.txt
CharActor.egg-info/requires.txt
CharActor.egg-info/top_level.txt
CharActor/_charactor/__init__.py
CharActor/_charactor/actor/__init__.py
CharActor/_charactor/actor/_actor/__init__.py
CharActor/_charactor/actor/_actor/_base_character.py
CharActor/_charactor/actor/_actor/_base_class_actors.py
CharActor/_charactor/actor/_actor/_base_race_actors.py
CharActor/_charactor/actor/_actor/base_actor.py
CharActor/_charactor/actor/_actor/character/__init__.py
CharActor/_charactor/actor/_actor/character/attributes/__init__.py
CharActor/_charactor/actor/_actor/character/attributes/ability.py
CharActor/_charactor/actor/_actor/character/attributes/alignment.py
CharActor/_charactor/actor/_actor/character/attributes/background.py
CharActor/_charactor/actor/_actor/character/attributes/inventory.py
CharActor/_charactor/actor/_actor/character/attributes/race.py
CharActor/_charactor/actor/_actor/character/attributes/role.py
CharActor/_charactor/actor/_actor/character/attributes/skill.py
CharActor/_charactor/actor/_actor/character/attributes/spell.py
CharActor/_charactor/dicts/__init__.py
CharActor/_charactor/dicts/alignments.json
CharActor/_charactor/dicts/backgrounds.json
CharActor/_charactor/dicts/kinds.json
CharActor/_charactor/dicts/levels.json
CharActor/_charactor/dicts/race_attributes.json
CharActor/_charactor/dicts/role_attributes.json
CharActor/_charactor/dicts/skills.json
CharActor/_charactor/dicts/spells.json
CharActor/_charactor/dicts/subrace_attributes.json
CharActor/_charactor/dicts/traits.json