Metadata-Version: 2.1
Name: CharActor
Version: 0.9.9
Summary: A module for creating and managing rpg characters.
Home-page: https://github.com/primal-coder/CharActor
Author: James Evans
Author-email: joesaysahoy@gmail.com
Keywords: rpg character dnd d&d dungeons and dragons dungeons & dragons player character actor charactor
Classifier: Development Status :: 3 - Alpha
Classifier: Intended Audience :: Developers
Classifier: Topic :: Games/Entertainment :: Role-Playing
Classifier: License :: OSI Approved :: MIT License
Classifier: Programming Language :: Python :: 3.8
Requires-Python: >=3.8
Requires-Dist: dicepy
Requires-Dist: entyty
Requires-Dist: CharObj
Requires-Dist: getch
Requires-Dist: pyglet
Requires-Dist: pymunk
